odoo8_addon_mass_mailing_custom_unsubscribe-8.0.2.1.0-py2.7-nspkg.pth
odoo_addons/mass_mailing_custom_unsubscribe/__openerp__.py
odoo_addons/mass_mailing_custom_unsubscribe/__init__.py
odoo_addons/mass_mailing_custom_unsubscribe/exceptions.py
odoo_addons/mass_mailing_custom_unsubscribe/README.rst
odoo_addons/mass_mailing_custom_unsubscribe/security/ir.model.access.csv
odoo_addons/mass_mailing_custom_unsubscribe/migrations/8.0.2.0.0/pre-migrate.py
odoo_addons/mass_mailing_custom_unsubscribe/models/mail_unsubscription.py
odoo_addons/mass_mailing_custom_unsubscribe/models/mail_mail.py
odoo_addons/mass_mailing_custom_unsubscribe/models/mail_mass_mailing_list.py
odoo_addons/mass_mailing_custom_unsubscribe/models/__init__.py
odoo_addons/mass_mailing_custom_unsubscribe/models/mail_mass_mailing.py
odoo_addons/mass_mailing_custom_unsubscribe/i18n/ja.po
odoo_addons/mass_mailing_custom_unsubscribe/i18n/lv.po
odoo_addons/mass_mailing_custom_unsubscribe/i18n/zh_CN.po
odoo_addons/mass_mailing_custom_unsubscribe/i18n/nb_NO.po
odoo_addons/mass_mailing_custom_unsubscribe/i18n/uk.po
odoo_addons/mass_mailing_custom_unsubscribe/i18n/es_AR.po
odoo_addons/mass_mailing_custom_unsubscribe/i18n/ko.po
odoo_addons/mass_mailing_custom_unsubscribe/i18n/tr_TR.po
odoo_addons/mass_mailing_custom_unsubscribe/i18n/ru.po
odoo_addons/mass_mailing_custom_unsubscribe/i18n/gl_ES.po
odoo_addons/mass_mailing_custom_unsubscribe/i18n/pt.po
odoo_addons/mass_mailing_custom_unsubscribe/i18n/fr_CH.po
odoo_addons/mass_mailing_custom_unsubscribe/i18n/it.po
odoo_addons/mass_mailing_custom_unsubscribe/i18n/es_CL.po
odoo_addons/mass_mailing_custom_unsubscribe/i18n/es.po
odoo_addons/mass_mailing_custom_unsubscribe/i18n/nl_BE.po
odoo_addons/mass_mailing_custom_unsubscribe/i18n/fr_FR.po
odoo_addons/mass_mailing_custom_unsubscribe/i18n/ar.po
odoo_addons/mass_mailing_custom_unsubscribe/i18n/lt.po
odoo_addons/mass_mailing_custom_unsubscribe/i18n/vi_VN.po
odoo8_addon_mass_mailing_custom_unsubscribe-8.0.2.1.0.dist-info/top_level.txt
odoo8_addon_mass_mailing_custom_unsubscribe-8.0.2.1.0.dist-info/WHEEL
odoo8_addon_mass_mailing_custom_unsubscribe-8.0.2.1.0.dist-info/RECORD
odoo8_addon_mass_mailing_custom_unsubscribe-8.0.2.1.0.dist-info/metadata.json
odoo8_addon_mass_mailing_custom_unsubscribe-8.0.2.1.0.dist-info/DESCRIPTION.rst
odoo8_addon_mass_mailing_custom_unsubscribe-8.0.2.1.0.dist-info/METADATA
odoo8_addon_mass_mailing_custom_unsubscribe-8.0.2.1.0.dist-info/namespace_packages.txt
