Metadata-Version: 2.0
Name: odoo8-addon-mass-mailing-custom-unsubscribe
Version: 8.0.2.1.0
Summary: Customizable unsubscription process on mass mailing emails
Home-page: http://www.antiun.com
Author: Antiun Ingeniería S.L., Tecnativa,Odoo Community Association (OCA)
Author-email: support@odoo-community.org
License: AGPL-3
Platform: UNKNOWN
Requires-Dist: odoo (<9.0a,>=8.0a)
Classifier: Programming Language :: Python :: 2.7
Classifier: Framework :: Odoo
Classifier: License :: OSI Approved :: GNU Affero General Public License v3
